<?xml version="1.0"?>
<import>
  <BACovLookup public-id="z07i2e0944f89acegp58dut3t3a">
    <Availability>Available</Availability>
    <CoveragePatternCode>CADeathDisabilityCov</CoveragePatternCode>
    <EndEffectiveDate/>
    <PolicyLinePatternCode>BusinessAutoLine</PolicyLinePatternCode>
    <StartEffectiveDate>2000-01-01 00:00:00.000</StartEffectiveDate>
    <State>SD</State>
  </BACovLookup>
  <BACovLookup public-id="zjth0f8ae0g952san7a8avji1qb">
    <Availability>Available</Availability>
    <CoveragePatternCode>CADeathDisabilityCov</CoveragePatternCode>
    <EndEffectiveDate/>
    <JobType/>
    <PolicyLinePatternCode>BusinessAutoLine</PolicyLinePatternCode>
    <PolicyType/>
    <StartEffectiveDate>2000-01-01 00:00:00.000</StartEffectiveDate>
    <State>TX</State>
    <UWCompanyCode/>
  </BACovLookup>
  <CovTermLookup public-id="zamga9obqvj9s0imnkcq4pned59">
    <Availability>Available</Availability>
    <CovTermPatternCode>DeathBenefitLimit</CovTermPatternCode>
    <EndEffectiveDate/>
    <PolicyLinePatternCode>BusinessAutoLine</PolicyLinePatternCode>
    <StartEffectiveDate>2000-01-01 00:00:00.000</StartEffectiveDate>
    <State>SD</State>
  </CovTermLookup>
  <CovTermOptLookup public-id="ztjhu3nk0v03s0hs2p1rdv6e6u9">
    <Availability>Available</Availability>
    <CovTermOptCode>zkkgct9giridaa8gpd6svgrkfv9</CovTermOptCode>
    <CovTermPatternCode>DeathBenefitLimit</CovTermPatternCode>
    <EndEffectiveDate/>
    <StartEffectiveDate>2000-01-01 00:00:00.000</StartEffectiveDate>
    <State/>
    <Currency>usd</Currency>
  </CovTermOptLookup>
  <CovTermOptLookup public-id="za3h6k5i3ghc18nksbb2edjvnj9">
    <Availability>Available</Availability>
    <CovTermOptCode>zhsikili17tbv5q54793fs7gpib</CovTermOptCode>
    <CovTermPatternCode>DeathBenefitLimit</CovTermPatternCode>
    <EndEffectiveDate/>
    <StartEffectiveDate>2000-01-01 00:00:00.000</StartEffectiveDate>
    <State/>
    <Currency>usd</Currency>
  </CovTermOptLookup>
  <CovTermOptLookup public-id="z8lj2erm1ovro84837fgkb9ti9a">
    <Availability>Available</Availability>
    <CovTermOptCode>zmhiuhuo1546odh34v28pllgdv9</CovTermOptCode>
    <CovTermPatternCode>DeathBenefitLimit</CovTermPatternCode>
    <EndEffectiveDate/>
    <StartEffectiveDate>2000-01-01 00:00:00.000</StartEffectiveDate>
    <State/>
    <Currency>usd</Currency>
  </CovTermOptLookup>
  <CovTermLookup public-id="zpghq1pp5j502156jrec27rkvla">
    <Availability>Available</Availability>
    <CovTermPatternCode>DisabilityBenefitLimit</CovTermPatternCode>
    <EndEffectiveDate/>
    <PolicyLinePatternCode>BusinessAutoLine</PolicyLinePatternCode>
    <StartEffectiveDate>2000-01-01 00:00:00.000</StartEffectiveDate>
    <State>SD</State>
  </CovTermLookup>
  <CovTermOptLookup public-id="zvvgmhc82b5pf8t06bg2es4jsl9">
    <Availability>Available</Availability>
    <CovTermOptCode>zubgq1d3qh5q121las0qosn4rt9</CovTermOptCode>
    <CovTermPatternCode>DisabilityBenefitLimit</CovTermPatternCode>
    <EndEffectiveDate/>
    <StartEffectiveDate>2000-01-01 00:00:00.000</StartEffectiveDate>
    <State/>
    <Currency>usd</Currency>
  </CovTermOptLookup>
  <CovTermLookup public-id="zchjc5d7l108i9nv2akiaf5t9la">
    <Availability>Available</Availability>
    <CovTermPatternCode>DeathBenefitLimit</CovTermPatternCode>
    <EndEffectiveDate/>
    <JobType/>
    <PolicyLinePatternCode>BusinessAutoLine</PolicyLinePatternCode>
    <StartEffectiveDate>2000-01-01 00:00:00.000</StartEffectiveDate>
    <State>TX</State>
    <UWCompanyCode/>
  </CovTermLookup>
  <CovTermLookup public-id="z65ge7gr5gued3n5tn7navsivj8">
    <Availability>Available</Availability>
    <CovTermPatternCode>DisabilityBenefitLimit</CovTermPatternCode>
    <EndEffectiveDate/>
    <JobType/>
    <PolicyLinePatternCode>BusinessAutoLine</PolicyLinePatternCode>
    <StartEffectiveDate>2000-01-01 00:00:00.000</StartEffectiveDate>
    <State>TX</State>
    <UWCompanyCode/>
  </CovTermLookup>
</import>